working/__init__.py
working-0.1.1.dist-info/METADATA
working-0.1.1.dist-info/RECORD
working-0.1.1.dist-info/WHEEL
working-0.1.1.dist-info/top_level.txt
